cipher/__init__.py
cipher/__main__.py
cipher/ui.py
cipher/utilities.py
cipher_asymmetric-0.0.5.dist-info/METADATA
cipher_asymmetric-0.0.5.dist-info/WHEEL
cipher_asymmetric-0.0.5.dist-info/entry_points.txt
cipher_asymmetric-0.0.5.dist-info/top_level.txt
cipher_asymmetric-0.0.5.dist-info/RECORD
