Metadata-Version: 2.1
Name: cipher-asymmetric
Version: 0.0.5
Summary: A Python CLI utility made for file encryption
Home-page: https://github.com/Programming-geek582/cipher-asymmetric
Author: PG
Author-email: htmlgeek752@gmail.com
Classifier: Programming Language :: Python :: 3
Classifier: License :: OSI Approved :: MIT License
Classifier: Operating System :: OS Independent
Classifier: Programming Language :: Python :: 3.8
Requires: cryptography
Requires: click
Requires-Python: >=3.8
